.DS_Store
pystout/__init__.py
pystout/pystout.py
pystout-0.0.8.dist-info/LICENSE.md
pystout-0.0.8.dist-info/METADATA
pystout-0.0.8.dist-info/WHEEL
pystout-0.0.8.dist-info/top_level.txt
pystout-0.0.8.dist-info/RECORD
