Metadata-Version: 2.1
Name: pystout
Version: 0.0.8
Summary: A Package To Make Publication Quality Latex Tables From Python Regression Output
Home-page: https://github.com/lucashusted/pystout
Author: Lucas Husted
Author-email: lucas.f.husted@columbia.edu
License: GNU
Platform: UNKNOWN
Classifier: Development Status :: 3 - Alpha
Classifier: Intended Audience :: End Users/Desktop
Classifier: Intended Audience :: Financial and Insurance Industry
Classifier: Intended Audience :: Science/Research
Classifier: Programming Language :: Python :: 3.6
Classifier: Programming Language :: Python :: 3.7
Classifier: Programming Language :: Python :: 3.8
Classifier: Operating System :: MacOS :: MacOS X
Classifier: Operating System :: Microsoft :: Windows
Classifier: Operating System :: POSIX
Classifier: Programming Language :: Python
Classifier: Topic :: Scientific/Engineering
Requires-Python: >=3
Requires-Dist: numpy
Requires-Dist: pandas (>=0.25)
